better_wget/__init__.py
better_wget/__main__.py
better_wget/download.py
bwget-0.0.1.dist-info/LICENSE
bwget-0.0.1.dist-info/METADATA
bwget-0.0.1.dist-info/WHEEL
bwget-0.0.1.dist-info/entry_points.txt
bwget-0.0.1.dist-info/top_level.txt
bwget-0.0.1.dist-info/RECORD
