Metadata-Version: 2.1
Name: bwget
Version: 0.0.1
Summary: Improved wget
Home-page: https://github.com/plant99/better-wget
Author: plant99
Author-email: shivashispadhi@gmail.com
License: UNKNOWN
Platform: UNKNOWN
Classifier: Programming Language :: Python :: 3
Classifier: License :: OSI Approved :: MIT License
Classifier: Operating System :: OS Independent
